setup.py
bin/ds_download.py
bin/ds_status.py
bin/ds_upload.py
dsapi/__init__.py
dsapi/dsapi.py
dsapi.egg-info/PKG-INFO
dsapi.egg-info/SOURCES.txt
dsapi.egg-info/dependency_links.txt
dsapi.egg-info/not-zip-safe
dsapi.egg-info/requires.txt
dsapi.egg-info/top_level.txt