Metadata-Version: 1.1
Name: dsapi
Version: 0.6-beta
Summary: Ingenuity Upload and Status Python Helper scripts and DatastreamAPI library
Home-page: https://github.com/QIAGENDatastream/dsapi
Author: Chris Harris
Author-email: Chris.Harris@Qiagen.com
License: GPLv3
Download-URL: https://github.com/QIAGENDatastream/dsapi/archive/v0.6-beta.tar.gz
Platform: UNKNOWN
